rules_engine/__init__.py
rules_engine/rules_engine.py
funnel_rules_engine-1.3.1.dist-info/LICENSE.md
funnel_rules_engine-1.3.1.dist-info/METADATA
funnel_rules_engine-1.3.1.dist-info/WHEEL
funnel_rules_engine-1.3.1.dist-info/top_level.txt
funnel_rules_engine-1.3.1.dist-info/RECORD
