Metadata-Version: 2.1
Name: funnel_rules_engine
Version: 1.3.1
Summary: A simple, generic rules engine.
Home-page: https://github.com/funnel-io/funnel-rules-engine
Author: The Funnel Dev Team
Author-email: open-source@funnel.io
License: MIT
Project-URL: Bug Reports, https://github.com/funnel-io/funnel-rules-engine/issues
Project-URL: Source, https://github.com/funnel-io/funnel-rules-engine
Keywords: ["rules engine"]
Classifier: Development Status :: 5 - Production/Stable
Classifier: License :: OSI Approved :: MIT License
Classifier: Programming Language :: Python :: 3
Classifier: Programming Language :: Python :: 3.8
Classifier: Programming Language :: Python :: 3.9
Classifier: Programming Language :: Python :: 3.10
Classifier: Programming Language :: Python :: 3.11
Classifier: Programming Language :: Python :: 3.12
Classifier: Topic :: Software Development :: Libraries
License-File: LICENSE.md
